mcp_toolbox_cli/__init__.py
mcp_toolbox_cli/cli.py
mcp_toolbox_cli/client.py
mcp_toolbox_cli/config.py
mcp_toolbox_cli-0.1.0.dist-info/licenses/LICENSE
mcp_toolbox_cli-0.1.0.dist-info/METADATA
mcp_toolbox_cli-0.1.0.dist-info/WHEEL
mcp_toolbox_cli-0.1.0.dist-info/entry_points.txt
mcp_toolbox_cli-0.1.0.dist-info/top_level.txt
mcp_toolbox_cli-0.1.0.dist-info/RECORD
