Metadata-Version: 2.4
Name: mcp-toolbox-cli
Version: 0.1.0
Summary: CLI tool for uploading and managing MCP tools on MCP ToolBox platform
Author-email: MCP ToolBox <muldercw@gmail.com>
License-Expression: MIT
Project-URL: Homepage, https://muldercw.com
Project-URL: Repository, https://github.com/muldercw/mcp-toolbox-cli
Project-URL: Issues, https://github.com/muldercw/mcp-toolbox-cli/issues
Keywords: mcp,tools,cli,model-context-protocol,toolbox
Classifier: Development Status :: 4 - Beta
Classifier: Intended Audience :: Developers
Classifier: Programming Language :: Python :: 3
Classifier: Programming Language :: Python :: 3.8
Classifier: Programming Language :: Python :: 3.9
Classifier: Programming Language :: Python :: 3.10
Classifier: Programming Language :: Python :: 3.11
Classifier: Programming Language :: Python :: 3.12
Requires-Python: >=3.8
License-File: LICENSE
Requires-Dist: click>=8.0.0
Requires-Dist: requests>=2.28.0
Requires-Dist: rich>=13.0.0
Requires-Dist: tqdm>=4.64.0
Provides-Extra: dev
Requires-Dist: pytest>=7.0.0; extra == "dev"
Requires-Dist: black>=22.0.0; extra == "dev"
Requires-Dist: flake8>=4.0.0; extra == "dev"
Dynamic: license-file
